<?xml version="1.0" encoding="UTF-8"?>
<repomd xmlns="http://linux.duke.edu/metadata/repo">
  <data type="other">
    <location href="repodata/other.xml.gz"/>
    <checksum type="sha">57f36c7b2eb749bed90e36d816cbb16c965ba577</checksum>
    <timestamp>1435833775</timestamp>
    <open-checksum type="sha">eed4682302cfcca8d7778aef9f368c194ebf647f</open-checksum>
  </data>
  <data type="filelists">
    <location href="repodata/filelists.xml.gz"/>
    <checksum type="sha">0355511846982d6fd78a30cd66e27a3e425923de</checksum>
    <timestamp>1435833775</timestamp>
    <open-checksum type="sha">2e1f41736681cccf146421049504b4ce31e93868</open-checksum>
  </data>
  <data type="primary">
    <location href="repodata/primary.xml.gz"/>
    <checksum type="sha">977512706dffdac8281a16899a25d671deb6a100</checksum>
    <timestamp>1435833775</timestamp>
    <open-checksum type="sha">92df3fc786b57dd4503487f0aeff5f889fcc13a3</open-checksum>
  </data>
</repomd>
